LeetcodeCookbookFix1/README.md
LeetcodeCookbookFix1/__init__.py
LeetcodeCookbookFix1/__main__.py
LeetcodeCookbookFix1/file.epub
LeetcodeCookbookFix1/index.html
LeetcodeCookbookFix1/css/__init__.py
LeetcodeCookbookFix1/css/annotations.css
LeetcodeCookbookFix1/css/main.css
LeetcodeCookbookFix1/css/normalize.css
LeetcodeCookbookFix1/css/popup.css
LeetcodeCookbookFix1/font/__init__.py
LeetcodeCookbookFix1/font/fontello.eot
LeetcodeCookbookFix1/font/fontello.svg
LeetcodeCookbookFix1/font/fontello.ttf
LeetcodeCookbookFix1/font/fontello.woff
LeetcodeCookbookFix1/img/__init__.py
LeetcodeCookbookFix1/img/annotator-glyph-sprite.png
LeetcodeCookbookFix1/img/annotator-icon-sprite.png
LeetcodeCookbookFix1/img/apple-touch-icon.png
LeetcodeCookbookFix1/img/cancelfullscreen.png
LeetcodeCookbookFix1/img/close.png
LeetcodeCookbookFix1/img/fullscreen.png
LeetcodeCookbookFix1/img/loader.gif
LeetcodeCookbookFix1/img/menu-icon.png
LeetcodeCookbookFix1/img/save.png
LeetcodeCookbookFix1/img/saved.png
LeetcodeCookbookFix1/img/settings-s.png
LeetcodeCookbookFix1/img/settings.png
LeetcodeCookbookFix1/img/star.png
LeetcodeCookbookFix1/js/__init__.py
LeetcodeCookbookFix1/js/epub.js
LeetcodeCookbookFix1/js/epub.min.js
LeetcodeCookbookFix1/js/epub.min.map
LeetcodeCookbookFix1/js/hooks.min.js
LeetcodeCookbookFix1/js/hooks.min.map
LeetcodeCookbookFix1/js/reader.js
LeetcodeCookbookFix1/js/reader.js.map
LeetcodeCookbookFix1/js/reader.min.js
LeetcodeCookbookFix1/js/reader.min.map
LeetcodeCookbookFix1/js/hooks/__init__.py
LeetcodeCookbookFix1/js/hooks/extensions/__init__.py
LeetcodeCookbookFix1/js/hooks/extensions/highlight.js
LeetcodeCookbookFix1/js/libs/__init__.py
LeetcodeCookbookFix1/js/libs/jquery.min.js
LeetcodeCookbookFix1/js/libs/localforage.min.js
LeetcodeCookbookFix1/js/libs/screenfull.js
LeetcodeCookbookFix1/js/libs/screenfull.min.js
LeetcodeCookbookFix1/js/libs/zip.min.js
LeetcodeCookbookFix1/js/plugins/__init__.py
LeetcodeCookbookFix1/js/plugins/hypothesis.js
leetcode_cookbook_fix1-2025.3.25.0.dist-info/METADATA
leetcode_cookbook_fix1-2025.3.25.0.dist-info/WHEEL
leetcode_cookbook_fix1-2025.3.25.0.dist-info/entry_points.txt
leetcode_cookbook_fix1-2025.3.25.0.dist-info/top_level.txt
leetcode_cookbook_fix1-2025.3.25.0.dist-info/RECORD
